{
    "scene_alley_start": {
        "entity": "system",
        "content": "[speed=0.3]Connecting to neural uplink...[wait=0.8] established.",
        "next_id": "intro_cinematic",
        "metadata": {
            "bg": "alley_bg",
            "bgm": "neon_noir",
            "hide_ui": "false",
            "auto_next": "true"
        }
    },

    "intro_cinematic": {
        "entity": "system",
        "content": "[shake]WARNING:[wait=0.5] System integrity compromised.",
        "next_id": "alley_start_real",
        "metadata": {
            "hide_ui": "false",
            "auto_next": "true"
        },
        "events": [
            { "op": "shake", "value": 10 },
            { "op": "delay", "value": 1500 }
        ]
    },

    "alley_start_real": {
        "entity": "akira",
        "content": "Kael! Stay back! Something is [font=dream]wrong[/font] with the uplink.",
        "next_id": "kael_enters",
        "metadata": {
            "expression": "serious",
            "pos": "left"
        },
        "events": [
            { "op": "fade", "var": "akira", "value_str": "1.0", "value": 1000 }
        ]
    },

    "kael_enters": {
        "entity": "kael",
        "content": "I can feel it too... it's like a [color=#ff00ff]glitch[/color] in the air.",
        "next_id": "alley_move_demo",
        "metadata": {
            "join": "true",
            "expression": "idle",
            "pos": "right"
        },
        "events": [
            { "op": "fade", "var": "kael", "value_str": "1.0", "value": 800 }
        ]
    },

    "alley_move_demo": {
        "entity": "akira",
        "content": "Wait, I'm detecting a signature nearby. Let's move in.",
        "next_id": "alley_to_market",
        "metadata": { "join": "true" },
        "events": [
            { "op": "move", "var": "akira", "value_str": "center", "value": 500 },
            { "op": "move", "var": "kael", "value_str": "0.9", "value": 400 }
        ]
    },

    "alley_to_market": {
        "entity": "system",
        "content": "Moving to the Market District...",
        "next_id": "scene_market_start",
        "metadata": {
            "auto_next": "true",
            "join": "true"
        },
        "events": [
            { "op": "fade", "var": "bg", "value_str": "market_bg", "value": 2000 },
            { "op": "fade", "var": "akira", "value_str": "0.0", "value": 1500 },
            { "op": "fade", "var": "kael", "value_str": "0.0", "value": 1500 },
            { "op": "delay", "value": 1500 }
        ]
    },

    "scene_market_start": {
        "entity": "akira",
        "content": "The market is unusually quiet today. [font=dream]Eerily quiet.[/font]",
        "next_id": "market_options",
        "metadata": {
            "expression": "idle",
            "pos": "left",
            "alpha": "0"
        },
        "events": [
            { "op": "fade", "var": "akira", "value_str": "1.0", "value": 500 }
        ]
    },

    "market_options": {
        "entity": "akira",
        "content": "What's our next move?",
        "options": [
            { "content": "Search the stalls", "next_id": "market_browsing" },
            { "content": "Check the terminal", "next_id": "market_terminal", "style": "premium" }
        ]
    },

    "market_browsing": {
        "entity": "kael",
        "content": "Nothing but scrap metal and rusted parts.",
        "next_id": "dialog_end_final",
        "metadata": { "join": "true", "pos": "right" }
    },

    "market_terminal": {
        "entity": "akira",
        "content": "Accessing the main terminal... [wait=0.5] [font=dream]ACCESS GRANTED[/font].",
        "next_id": "dialog_end_final"
    },

    "dialog_end_final": {
        "entity": "system",
        "content": "End of Demonstration.",
        "next_id": "dialog_end"
    }
}
